{
  "execution": {
    "timestamp": "2025-09-25T17:37:44.935Z",
    "projectRoot": "/Users/jeremyparker/infinite-continue-stop-hook",
    "hookVersion": "1.0.0",
    "nodeVersion": "v22.20.0",
    "platform": "darwin",
    "arch": "arm64",
    "pid": 48768,
    "cwd": "/Users/jeremyparker/infinite-continue-stop-hook",
    "endTimestamp": "2025-09-25T17:37:44.935Z",
    "durationMs": 0
  },
  "input": {},
  "projectState": {},
  "decisions": [],
  "flow": [
    {
      "timestamp": "2025-09-25T17:37:44.935Z",
      "message": "ERROR in autoSortTasksByPriority: Validation failed: Task error_1758821864933_nhpa7j7bf: Required field 'category' is missing, Task error_1758821864934_eed1xbdnj: Required field 'category' is missing, Task test_1758821864934_ugu7uqflc: Required field 'category' is missing, Task test_1758821864934_6b66z7fos: Required field 'category' is missing, Task test_1758821864934_cpxslfci6: Required field 'category' is missing, Task test_1758821864934_98w51ilbp: Required field 'category' is missing, Task test_1758821864934_cald7m6tm: Required field 'category' is missing, Task test_1758821864934_mz73a2093: Required field 'category' is missing, Task test_1758821864934_zls4mfwxm: Required field 'category' is missing"
    }
  ],
  "output": {},
  "errors": [
    {
      "timestamp": "2025-09-25T17:37:44.935Z",
      "context": "autoSortTasksByPriority",
      "message": "Validation failed: Task error_1758821864933_nhpa7j7bf: Required field 'category' is missing, Task error_1758821864934_eed1xbdnj: Required field 'category' is missing, Task test_1758821864934_ugu7uqflc: Required field 'category' is missing, Task test_1758821864934_6b66z7fos: Required field 'category' is missing, Task test_1758821864934_cpxslfci6: Required field 'category' is missing, Task test_1758821864934_98w51ilbp: Required field 'category' is missing, Task test_1758821864934_cald7m6tm: Required field 'category' is missing, Task test_1758821864934_mz73a2093: Required field 'category' is missing, Task test_1758821864934_zls4mfwxm: Required field 'category' is missing",
      "stack": "Error: Validation failed: Task error_1758821864933_nhpa7j7bf: Required field 'category' is missing, Task error_1758821864934_eed1xbdnj: Required field 'category' is missing, Task test_1758821864934_ugu7uqflc: Required field 'category' is missing, Task test_1758821864934_6b66z7fos: Required field 'category' is missing, Task test_1758821864934_cpxslfci6: Required field 'category' is missing, Task test_1758821864934_98w51ilbp: Required field 'category' is missing, Task test_1758821864934_cald7m6tm: Required field 'category' is missing, Task test_1758821864934_mz73a2093: Required field 'category' is missing, Task test_1758821864934_zls4mfwxm: Required field 'category' is missing\n    at TaskManager.writeTodo (/Users/jeremyparker/infinite-continue-stop-hook/lib/taskManager.js:211:17)\n    at autoSortTasksByPriority (/Users/jeremyparker/infinite-continue-stop-hook/stop-hook.js:464:25)\n    at async Socket.<anonymous> (/Users/jeremyparker/infinite-continue-stop-hook/stop-hook.js:946:26)",
      "name": "Error"
    }
  ]
}