{
  "execution": {
    "timestamp": "2025-09-25T17:36:39.060Z",
    "projectRoot": "/Users/jeremyparker/infinite-continue-stop-hook",
    "hookVersion": "1.0.0",
    "nodeVersion": "v22.20.0",
    "platform": "darwin",
    "arch": "arm64",
    "pid": 46964,
    "cwd": "/Users/jeremyparker/infinite-continue-stop-hook",
    "endTimestamp": "2025-09-25T17:36:39.060Z",
    "durationMs": 0
  },
  "input": {},
  "projectState": {},
  "decisions": [],
  "flow": [
    {
      "timestamp": "2025-09-25T17:36:39.060Z",
      "message": "ERROR in autoSortTasksByPriority: Validation failed: Task error_1758821799059_3q3fr1bua: Required field 'category' is missing, Task error_1758821799059_idhiho4s5: Required field 'category' is missing, Task test_1758821799059_h6picw44h: Required field 'category' is missing, Task test_1758821799059_plcb7n032: Required field 'category' is missing, Task test_1758821799059_y1egk3xnl: Required field 'category' is missing, Task test_1758821799059_qj36ocivp: Required field 'category' is missing, Task test_1758821799059_v295aq8z0: Required field 'category' is missing, Task test_1758821799059_myrbul6br: Required field 'category' is missing, Task test_1758821799059_h8ie0t030: Required field 'category' is missing"
    }
  ],
  "output": {},
  "errors": [
    {
      "timestamp": "2025-09-25T17:36:39.060Z",
      "context": "autoSortTasksByPriority",
      "message": "Validation failed: Task error_1758821799059_3q3fr1bua: Required field 'category' is missing, Task error_1758821799059_idhiho4s5: Required field 'category' is missing, Task test_1758821799059_h6picw44h: Required field 'category' is missing, Task test_1758821799059_plcb7n032: Required field 'category' is missing, Task test_1758821799059_y1egk3xnl: Required field 'category' is missing, Task test_1758821799059_qj36ocivp: Required field 'category' is missing, Task test_1758821799059_v295aq8z0: Required field 'category' is missing, Task test_1758821799059_myrbul6br: Required field 'category' is missing, Task test_1758821799059_h8ie0t030: Required field 'category' is missing",
      "stack": "Error: Validation failed: Task error_1758821799059_3q3fr1bua: Required field 'category' is missing, Task error_1758821799059_idhiho4s5: Required field 'category' is missing, Task test_1758821799059_h6picw44h: Required field 'category' is missing, Task test_1758821799059_plcb7n032: Required field 'category' is missing, Task test_1758821799059_y1egk3xnl: Required field 'category' is missing, Task test_1758821799059_qj36ocivp: Required field 'category' is missing, Task test_1758821799059_v295aq8z0: Required field 'category' is missing, Task test_1758821799059_myrbul6br: Required field 'category' is missing, Task test_1758821799059_h8ie0t030: Required field 'category' is missing\n    at TaskManager.writeTodo (/Users/jeremyparker/infinite-continue-stop-hook/lib/taskManager.js:211:17)\n    at autoSortTasksByPriority (/Users/jeremyparker/infinite-continue-stop-hook/stop-hook.js:464:25)\n    at async Socket.<anonymous> (/Users/jeremyparker/infinite-continue-stop-hook/stop-hook.js:946:26)",
      "name": "Error"
    }
  ]
}